mcp_server_tester/__init__.py
mcp_server_tester/__main__.py
mcp_server_tester/cli.py
mcp_server_tester/core.py
mcp_server_tester/exceptions.py
mcp_server_tester-1.4.3.dist-info/licenses/LICENSE
mcp_server_tester-1.4.3.dist-info/METADATA
mcp_server_tester-1.4.3.dist-info/WHEEL
mcp_server_tester-1.4.3.dist-info/entry_points.txt
mcp_server_tester-1.4.3.dist-info/top_level.txt
mcp_server_tester-1.4.3.dist-info/RECORD
