Metadata-Version: 2.4
Name: mcp-server-tester
Version: 1.4.3
Summary: Python wrapper for mcp-server-tester-sse-http-stdio NPM package
Author-email: stgmt <your-email@example.com>
License: MIT
Project-URL: Homepage, https://github.com/stgmt/mcp-server-tester-python
Project-URL: Bug Reports, https://github.com/stgmt/mcp-server-tester-python/issues
Project-URL: Source, https://github.com/stgmt/mcp-server-tester-python
Project-URL: NPM Package, https://www.npmjs.com/package/mcp-server-tester-sse-http-stdio
Keywords: mcp,model-context-protocol,testing,server-testing,sse,stdio,http,ai-tools,llm-tools
Classifier: Development Status :: 4 - Beta
Classifier: Intended Audience :: Developers
Classifier: License :: OSI Approved :: MIT License
Classifier: Programming Language :: Python :: 3
Classifier: Programming Language :: Python :: 3.8
Classifier: Programming Language :: Python :: 3.9
Classifier: Programming Language :: Python :: 3.10
Classifier: Programming Language :: Python :: 3.11
Classifier: Programming Language :: Python :: 3.12
Classifier: Topic :: Software Development :: Testing
Classifier: Topic :: Internet :: WWW/HTTP
Requires-Python: >=3.8
License-File: LICENSE
Requires-Dist: pyyaml>=6.0
Requires-Dist: click>=8.0.0
Requires-Dist: requests>=2.28.0
Provides-Extra: dev
Requires-Dist: pytest>=7.0.0; extra == "dev"
Requires-Dist: pytest-cov>=4.0.0; extra == "dev"
Requires-Dist: black>=23.0.0; extra == "dev"
Requires-Dist: flake8>=6.0.0; extra == "dev"
Requires-Dist: mypy>=1.0.0; extra == "dev"
Requires-Dist: types-PyYAML>=6.0.0; extra == "dev"
Dynamic: license-file
